{"repo": {"timestamp": 1763072343000}, "packages": {"network.loki.messenger": {"metadata": {"lastUpdated": 1763072343000}, "versions": {"bfbc92e49b3d4a4b478d8c72460e05336deec002ca072dc4c0f54c6d172e73be": null, "9982195d4e70fbbcd3efab62915c703c32669fbf573c0fa5a4f6372fbe3bbc2c": null, "042b021a37d882eb352ad5a2e6755bb1092db54b010b6496009b75504981990f": null, "67201c60883727c910c5727bbd65d3beb170acd59a3299a72ca41e49ae1d8012": null, "469139dbe423c01383edafabce15b0cdb6e0d1e11f528dad8d3afffb9c73ec6c": null, "b2ec9efc0b5c83c543e8a46781530420f207157883933a69318a1d281eb255cd": null, "c5384064eb9683768a7ad11406605fa0e8dec5f9a9eeb08026426687273f7af3": null, "91bb600dbb1dc66cf6348d71e2017a386fa38c623482635a9e4e9b0cebc40390": null, "4a4302bad72f2c75f324968e5a72aaad6ef7a4f881f24c2e3a91acc58d778955": null, "28f8e690a8e5f7e752a8d5ca43841563f58eb0607903c5c93f2c72a17af3bd27": null, "db142db3f4771813a79f4e441529a011ef7e9491fba6ac0fdf7a07e1559ffdf2": null, "976aa6729f58155c09283599d516baa849553f2c57dc156afce1e4ac46ef8f34": null, "66120c93e28e9e78f88c142f199901d7ab21bdb857f402f96e16c97edf455a40": null, "2f041c0e37f41b0d8749ee112b9ca34b2c560b099b668f646fb8a8b21c0b66b8": null, "fb406e6bfdc456b6ccd1069a93623a9f14b9eba553c8ba8b74b61e656c00f78c": null, "c20839c42917b54913404a496ad96e72f536273a57722a3e1c3856a20492bc32": {"added": 1763072341000, "file": {"name": "/session-1.29.1-universal-fdroid-release.apk", "sha256": "c20839c42917b54913404a496ad96e72f536273a57722a3e1c3856a20492bc32", "size": 147909706}, "manifest": {"nativecode": ["arm64-v8a", "armeabi-v7a", "x86", "x86_64"], "versionName": "1.29.1", "versionCode": 4305, "usesSdk": {"minSdkVersion": 26, "targetSdkVersion": 35}, "signer": {"sha256": ["f2a0ecf70686447d1d6c6cbbf58c42890500ccf41af372ae2099303980824edd"]}, "usesPermission": [{"name": "android.permission.ACCESS_NETWORK_STATE"}, {"name": "android.permission.BLUETOOTH"}, {"name": "android.permission.BROADCAST_STICKY"}, {"name": "android.permission.CAMERA"}, {"name": "android.permission.DISABLE_KEYGUARD"}, {"name": "android.permission.FOREGROUND_SERVICE"}, {"name": "android.permission.FOREGROUND_SERVICE_PHONE_CALL"}, {"name": "android.permission.FOREGROUND_SERVICE_MICROPHONE"}, {"name": "android.permission.FOREGROUND_SERVICE_SPECIAL_USE"}, {"name": "android.permission.MANAGE_OWN_CALLS"}, {"name": "com.android.launcher.permission.INSTALL_SHORTCUT"}, {"name": "android.permission.INTERNET"}, {"name": "android.app.role.DIALER"}, {"name": "android.permission.MODIFY_AUDIO_SETTINGS"}, {"name": "android.permission.POST_NOTIFICATIONS"}, {"name": "android.permission.RAISED_THREAD_PRIORITY"}, {"name": "android.permission.READ_EXTERNAL_STORAGE"}, {"name": "android.permission.READ_MEDIA_AUDIO"}, {"name": "android.permission.READ_MEDIA_IMAGES"}, {"name": "android.permission.READ_MEDIA_VIDEO"}, {"name": "android.permission.READ_MEDIA_VISUAL_USER_SELECTED"}, {"name": "android.permission.READ_SYNC_SETTINGS"}, {"name": "android.permission.RECEIVE_BOOT_COMPLETED"}, {"name": "android.permission.RECORD_AUDIO"}, {"name": "android.permission.REQUEST_IGNORE_BATTERY_OPTIMIZATIONS"}, {"name": "android.permission.USE_FINGERPRINT"}, {"name": "android.permission.USE_FULL_SCREEN_INTENT"}, {"name": "android.permission.VIBRATE"}, {"name": "android.permission.WAKE_LOCK"}, {"name": "android.permission.WRITE_EXTERNAL_STORAGE"}, {"name": "android.permission.WRITE_SYNC_SETTINGS"}, {"name": "com.google.android.c2dm.permission.RECEIVE"}, {"name": "network.loki.messenger.ACCESS_SESSION_SECRETS"}, {"name": "android.permission.USE_BIOMETRIC"}, {"name": "network.loki.messenger.DYNAMIC_RECEIVER_NOT_EXPORTED_PERMISSION"}]}}, "053a518dcdff066d2dfbf2c218a1e83566efcd3be90fda7cfc701e7a9195ad7a": {"added": 1763072343000, "file": {"name": "/session-1.29.1-x86_64-fdroid-release.apk", "sha256": "053a518dcdff066d2dfbf2c218a1e83566efcd3be90fda7cfc701e7a9195ad7a", "size": 82420875}, "manifest": {"nativecode": ["x86_64"], "versionName": "1.29.1", "versionCode": 4304, "usesSdk": {"minSdkVersion": 26, "targetSdkVersion": 35}, "signer": {"sha256": ["f2a0ecf70686447d1d6c6cbbf58c42890500ccf41af372ae2099303980824edd"]}, "usesPermission": [{"name": "android.permission.ACCESS_NETWORK_STATE"}, {"name": "android.permission.BLUETOOTH"}, {"name": "android.permission.BROADCAST_STICKY"}, {"name": "android.permission.CAMERA"}, {"name": "android.permission.DISABLE_KEYGUARD"}, {"name": "android.permission.FOREGROUND_SERVICE"}, {"name": "android.permission.FOREGROUND_SERVICE_PHONE_CALL"}, {"name": "android.permission.FOREGROUND_SERVICE_MICROPHONE"}, {"name": "android.permission.FOREGROUND_SERVICE_SPECIAL_USE"}, {"name": "android.permission.MANAGE_OWN_CALLS"}, {"name": "com.android.launcher.permission.INSTALL_SHORTCUT"}, {"name": "android.permission.INTERNET"}, {"name": "android.app.role.DIALER"}, {"name": "android.permission.MODIFY_AUDIO_SETTINGS"}, {"name": "android.permission.POST_NOTIFICATIONS"}, {"name": "android.permission.RAISED_THREAD_PRIORITY"}, {"name": "android.permission.READ_EXTERNAL_STORAGE"}, {"name": "android.permission.READ_MEDIA_AUDIO"}, {"name": "android.permission.READ_MEDIA_IMAGES"}, {"name": "android.permission.READ_MEDIA_VIDEO"}, {"name": "android.permission.READ_MEDIA_VISUAL_USER_SELECTED"}, {"name": "android.permission.READ_SYNC_SETTINGS"}, {"name": "android.permission.RECEIVE_BOOT_COMPLETED"}, {"name": "android.permission.RECORD_AUDIO"}, {"name": "android.permission.REQUEST_IGNORE_BATTERY_OPTIMIZATIONS"}, {"name": "android.permission.USE_FINGERPRINT"}, {"name": "android.permission.USE_FULL_SCREEN_INTENT"}, {"name": "android.permission.VIBRATE"}, {"name": "android.permission.WAKE_LOCK"}, {"name": "android.permission.WRITE_EXTERNAL_STORAGE"}, {"name": "android.permission.WRITE_SYNC_SETTINGS"}, {"name": "com.google.android.c2dm.permission.RECEIVE"}, {"name": "network.loki.messenger.ACCESS_SESSION_SECRETS"}, {"name": "android.permission.USE_BIOMETRIC"}, {"name": "network.loki.messenger.DYNAMIC_RECEIVER_NOT_EXPORTED_PERMISSION"}]}}, "28e72f0890ead5e4c3f64ca6edd6eeac119f8ac8edda7e0ef60da90677cd2aff": {"added": 1763072342000, "file": {"name": "/session-1.29.1-x86-fdroid-release.apk", "sha256": "28e72f0890ead5e4c3f64ca6edd6eeac119f8ac8edda7e0ef60da90677cd2aff", "size": 78159911}, "manifest": {"nativecode": ["x86"], "versionName": "1.29.1", "versionCode": 4303, "usesSdk": {"minSdkVersion": 26, "targetSdkVersion": 35}, "signer": {"sha256": ["f2a0ecf70686447d1d6c6cbbf58c42890500ccf41af372ae2099303980824edd"]}, "usesPermission": [{"name": "android.permission.ACCESS_NETWORK_STATE"}, {"name": "android.permission.BLUETOOTH"}, {"name": "android.permission.BROADCAST_STICKY"}, {"name": "android.permission.CAMERA"}, {"name": "android.permission.DISABLE_KEYGUARD"}, {"name": "android.permission.FOREGROUND_SERVICE"}, {"name": "android.permission.FOREGROUND_SERVICE_PHONE_CALL"}, {"name": "android.permission.FOREGROUND_SERVICE_MICROPHONE"}, {"name": "android.permission.FOREGROUND_SERVICE_SPECIAL_USE"}, {"name": "android.permission.MANAGE_OWN_CALLS"}, {"name": "com.android.launcher.permission.INSTALL_SHORTCUT"}, {"name": "android.permission.INTERNET"}, {"name": "android.app.role.DIALER"}, {"name": "android.permission.MODIFY_AUDIO_SETTINGS"}, {"name": "android.permission.POST_NOTIFICATIONS"}, {"name": "android.permission.RAISED_THREAD_PRIORITY"}, {"name": "android.permission.READ_EXTERNAL_STORAGE"}, {"name": "android.permission.READ_MEDIA_AUDIO"}, {"name": "android.permission.READ_MEDIA_IMAGES"}, {"name": "android.permission.READ_MEDIA_VIDEO"}, {"name": "android.permission.READ_MEDIA_VISUAL_USER_SELECTED"}, {"name": "android.permission.READ_SYNC_SETTINGS"}, {"name": "android.permission.RECEIVE_BOOT_COMPLETED"}, {"name": "android.permission.RECORD_AUDIO"}, {"name": "android.permission.REQUEST_IGNORE_BATTERY_OPTIMIZATIONS"}, {"name": "android.permission.USE_FINGERPRINT"}, {"name": "android.permission.USE_FULL_SCREEN_INTENT"}, {"name": "android.permission.VIBRATE"}, {"name": "android.permission.WAKE_LOCK"}, {"name": "android.permission.WRITE_EXTERNAL_STORAGE"}, {"name": "android.permission.WRITE_SYNC_SETTINGS"}, {"name": "com.google.android.c2dm.permission.RECEIVE"}, {"name": "network.loki.messenger.ACCESS_SESSION_SECRETS"}, {"name": "android.permission.USE_BIOMETRIC"}, {"name": "network.loki.messenger.DYNAMIC_RECEIVER_NOT_EXPORTED_PERMISSION"}]}}, "d8139df91dc877ccb7f0d74fdf11188051f40abaaf6e71b8fca03b3ddd344c4f": {"added": 1763072340000, "file": {"name": "/session-1.29.1-arm64-v8a-fdroid-release.apk", "sha256": "d8139df91dc877ccb7f0d74fdf11188051f40abaaf6e71b8fca03b3ddd344c4f", "size": 76915859}, "manifest": {"nativecode": ["arm64-v8a"], "versionName": "1.29.1", "versionCode": 4302, "usesSdk": {"minSdkVersion": 26, "targetSdkVersion": 35}, "signer": {"sha256": ["f2a0ecf70686447d1d6c6cbbf58c42890500ccf41af372ae2099303980824edd"]}, "usesPermission": [{"name": "android.permission.ACCESS_NETWORK_STATE"}, {"name": "android.permission.BLUETOOTH"}, {"name": "android.permission.BROADCAST_STICKY"}, {"name": "android.permission.CAMERA"}, {"name": "android.permission.DISABLE_KEYGUARD"}, {"name": "android.permission.FOREGROUND_SERVICE"}, {"name": "android.permission.FOREGROUND_SERVICE_PHONE_CALL"}, {"name": "android.permission.FOREGROUND_SERVICE_MICROPHONE"}, {"name": "android.permission.FOREGROUND_SERVICE_SPECIAL_USE"}, {"name": "android.permission.MANAGE_OWN_CALLS"}, {"name": "com.android.launcher.permission.INSTALL_SHORTCUT"}, {"name": "android.permission.INTERNET"}, {"name": "android.app.role.DIALER"}, {"name": "android.permission.MODIFY_AUDIO_SETTINGS"}, {"name": "android.permission.POST_NOTIFICATIONS"}, {"name": "android.permission.RAISED_THREAD_PRIORITY"}, {"name": "android.permission.READ_EXTERNAL_STORAGE"}, {"name": "android.permission.READ_MEDIA_AUDIO"}, {"name": "android.permission.READ_MEDIA_IMAGES"}, {"name": "android.permission.READ_MEDIA_VIDEO"}, {"name": "android.permission.READ_MEDIA_VISUAL_USER_SELECTED"}, {"name": "android.permission.READ_SYNC_SETTINGS"}, {"name": "android.permission.RECEIVE_BOOT_COMPLETED"}, {"name": "android.permission.RECORD_AUDIO"}, {"name": "android.permission.REQUEST_IGNORE_BATTERY_OPTIMIZATIONS"}, {"name": "android.permission.USE_FINGERPRINT"}, {"name": "android.permission.USE_FULL_SCREEN_INTENT"}, {"name": "android.permission.VIBRATE"}, {"name": "android.permission.WAKE_LOCK"}, {"name": "android.permission.WRITE_EXTERNAL_STORAGE"}, {"name": "android.permission.WRITE_SYNC_SETTINGS"}, {"name": "com.google.android.c2dm.permission.RECEIVE"}, {"name": "network.loki.messenger.ACCESS_SESSION_SECRETS"}, {"name": "android.permission.USE_BIOMETRIC"}, {"name": "network.loki.messenger.DYNAMIC_RECEIVER_NOT_EXPORTED_PERMISSION"}]}}, "ccb95619cf43930c995d4abb2a3200672e25c728e7ec6c23729be641b1848a56": {"added": 1763072340000, "file": {"name": "/session-1.29.1-armeabi-v7a-fdroid-release.apk", "sha256": "ccb95619cf43930c995d4abb2a3200672e25c728e7ec6c23729be641b1848a56", "size": 68361991}, "manifest": {"nativecode": ["armeabi-v7a"], "versionName": "1.29.1", "versionCode": 4301, "usesSdk": {"minSdkVersion": 26, "targetSdkVersion": 35}, "signer": {"sha256": ["f2a0ecf70686447d1d6c6cbbf58c42890500ccf41af372ae2099303980824edd"]}, "usesPermission": [{"name": "android.permission.ACCESS_NETWORK_STATE"}, {"name": "android.permission.BLUETOOTH"}, {"name": "android.permission.BROADCAST_STICKY"}, {"name": "android.permission.CAMERA"}, {"name": "android.permission.DISABLE_KEYGUARD"}, {"name": "android.permission.FOREGROUND_SERVICE"}, {"name": "android.permission.FOREGROUND_SERVICE_PHONE_CALL"}, {"name": "android.permission.FOREGROUND_SERVICE_MICROPHONE"}, {"name": "android.permission.FOREGROUND_SERVICE_SPECIAL_USE"}, {"name": "android.permission.MANAGE_OWN_CALLS"}, {"name": "com.android.launcher.permission.INSTALL_SHORTCUT"}, {"name": "android.permission.INTERNET"}, {"name": "android.app.role.DIALER"}, {"name": "android.permission.MODIFY_AUDIO_SETTINGS"}, {"name": "android.permission.POST_NOTIFICATIONS"}, {"name": "android.permission.RAISED_THREAD_PRIORITY"}, {"name": "android.permission.READ_EXTERNAL_STORAGE"}, {"name": "android.permission.READ_MEDIA_AUDIO"}, {"name": "android.permission.READ_MEDIA_IMAGES"}, {"name": "android.permission.READ_MEDIA_VIDEO"}, {"name": "android.permission.READ_MEDIA_VISUAL_USER_SELECTED"}, {"name": "android.permission.READ_SYNC_SETTINGS"}, {"name": "android.permission.RECEIVE_BOOT_COMPLETED"}, {"name": "android.permission.RECORD_AUDIO"}, {"name": "android.permission.REQUEST_IGNORE_BATTERY_OPTIMIZATIONS"}, {"name": "android.permission.USE_FINGERPRINT"}, {"name": "android.permission.USE_FULL_SCREEN_INTENT"}, {"name": "android.permission.VIBRATE"}, {"name": "android.permission.WAKE_LOCK"}, {"name": "android.permission.WRITE_EXTERNAL_STORAGE"}, {"name": "android.permission.WRITE_SYNC_SETTINGS"}, {"name": "com.google.android.c2dm.permission.RECEIVE"}, {"name": "network.loki.messenger.ACCESS_SESSION_SECRETS"}, {"name": "android.permission.USE_BIOMETRIC"}, {"name": "network.loki.messenger.DYNAMIC_RECEIVER_NOT_EXPORTED_PERMISSION"}]}}, "85774f5d82dbff45b3415b8ea529691eaefcc7c96d04a62ffb614c8ac235f86f": {"added": 1762321553000, "file": {"name": "/session-1.29.0-universal-fdroid-release.apk", "sha256": "85774f5d82dbff45b3415b8ea529691eaefcc7c96d04a62ffb614c8ac235f86f", "size": 147909706}, "manifest": {"nativecode": ["arm64-v8a", "armeabi-v7a", "x86", "x86_64"], "versionName": "1.29.0", "versionCode": 4295, "usesSdk": {"minSdkVersion": 26, "targetSdkVersion": 35}, "signer": {"sha256": ["f2a0ecf70686447d1d6c6cbbf58c42890500ccf41af372ae2099303980824edd"]}, "usesPermission": [{"name": "android.permission.ACCESS_NETWORK_STATE"}, {"name": "android.permission.BLUETOOTH"}, {"name": "android.permission.BROADCAST_STICKY"}, {"name": "android.permission.CAMERA"}, {"name": "android.permission.DISABLE_KEYGUARD"}, {"name": "android.permission.FOREGROUND_SERVICE"}, {"name": "android.permission.FOREGROUND_SERVICE_PHONE_CALL"}, {"name": "android.permission.FOREGROUND_SERVICE_MICROPHONE"}, {"name": "android.permission.FOREGROUND_SERVICE_SPECIAL_USE"}, {"name": "android.permission.MANAGE_OWN_CALLS"}, {"name": "com.android.launcher.permission.INSTALL_SHORTCUT"}, {"name": "android.permission.INTERNET"}, {"name": "android.app.role.DIALER"}, {"name": "android.permission.MODIFY_AUDIO_SETTINGS"}, {"name": "android.permission.POST_NOTIFICATIONS"}, {"name": "android.permission.RAISED_THREAD_PRIORITY"}, {"name": "android.permission.READ_EXTERNAL_STORAGE"}, {"name": "android.permission.READ_MEDIA_AUDIO"}, {"name": "android.permission.READ_MEDIA_IMAGES"}, {"name": "android.permission.READ_MEDIA_VIDEO"}, {"name": "android.permission.READ_MEDIA_VISUAL_USER_SELECTED"}, {"name": "android.permission.READ_SYNC_SETTINGS"}, {"name": "android.permission.RECEIVE_BOOT_COMPLETED"}, {"name": "android.permission.RECORD_AUDIO"}, {"name": "android.permission.REQUEST_IGNORE_BATTERY_OPTIMIZATIONS"}, {"name": "android.permission.USE_FINGERPRINT"}, {"name": "android.permission.USE_FULL_SCREEN_INTENT"}, {"name": "android.permission.VIBRATE"}, {"name": "android.permission.WAKE_LOCK"}, {"name": "android.permission.WRITE_EXTERNAL_STORAGE"}, {"name": "android.permission.WRITE_SYNC_SETTINGS"}, {"name": "com.google.android.c2dm.permission.RECEIVE"}, {"name": "network.loki.messenger.ACCESS_SESSION_SECRETS"}, {"name": "android.permission.USE_BIOMETRIC"}, {"name": "network.loki.messenger.DYNAMIC_RECEIVER_NOT_EXPORTED_PERMISSION"}]}}, "52c835a279472a28e74bf33edc546d7739316f5f03c925940cabfc922d4ce137": {"added": 1762321555000, "file": {"name": "/session-1.29.0-x86_64-fdroid-release.apk", "sha256": "52c835a279472a28e74bf33edc546d7739316f5f03c925940cabfc922d4ce137", "size": 82420871}, "manifest": {"nativecode": ["x86_64"], "versionName": "1.29.0", "versionCode": 4294, "usesSdk": {"minSdkVersion": 26, "targetSdkVersion": 35}, "signer": {"sha256": ["f2a0ecf70686447d1d6c6cbbf58c42890500ccf41af372ae2099303980824edd"]}, "usesPermission": [{"name": "android.permission.ACCESS_NETWORK_STATE"}, {"name": "android.permission.BLUETOOTH"}, {"name": "android.permission.BROADCAST_STICKY"}, {"name": "android.permission.CAMERA"}, {"name": "android.permission.DISABLE_KEYGUARD"}, {"name": "android.permission.FOREGROUND_SERVICE"}, {"name": "android.permission.FOREGROUND_SERVICE_PHONE_CALL"}, {"name": "android.permission.FOREGROUND_SERVICE_MICROPHONE"}, {"name": "android.permission.FOREGROUND_SERVICE_SPECIAL_USE"}, {"name": "android.permission.MANAGE_OWN_CALLS"}, {"name": "com.android.launcher.permission.INSTALL_SHORTCUT"}, {"name": "android.permission.INTERNET"}, {"name": "android.app.role.DIALER"}, {"name": "android.permission.MODIFY_AUDIO_SETTINGS"}, {"name": "android.permission.POST_NOTIFICATIONS"}, {"name": "android.permission.RAISED_THREAD_PRIORITY"}, {"name": "android.permission.READ_EXTERNAL_STORAGE"}, {"name": "android.permission.READ_MEDIA_AUDIO"}, {"name": "android.permission.READ_MEDIA_IMAGES"}, {"name": "android.permission.READ_MEDIA_VIDEO"}, {"name": "android.permission.READ_MEDIA_VISUAL_USER_SELECTED"}, {"name": "android.permission.READ_SYNC_SETTINGS"}, {"name": "android.permission.RECEIVE_BOOT_COMPLETED"}, {"name": "android.permission.RECORD_AUDIO"}, {"name": "android.permission.REQUEST_IGNORE_BATTERY_OPTIMIZATIONS"}, {"name": "android.permission.USE_FINGERPRINT"}, {"name": "android.permission.USE_FULL_SCREEN_INTENT"}, {"name": "android.permission.VIBRATE"}, {"name": "android.permission.WAKE_LOCK"}, {"name": "android.permission.WRITE_EXTERNAL_STORAGE"}, {"name": "android.permission.WRITE_SYNC_SETTINGS"}, {"name": "com.google.android.c2dm.permission.RECEIVE"}, {"name": "network.loki.messenger.ACCESS_SESSION_SECRETS"}, {"name": "android.permission.USE_BIOMETRIC"}, {"name": "network.loki.messenger.DYNAMIC_RECEIVER_NOT_EXPORTED_PERMISSION"}]}}, "8eed1c0e9a11367ca496d8f6372dae7805a6bb4f022319de4c139e61f45c8caf": {"added": 1762321554000, "file": {"name": "/session-1.29.0-x86-fdroid-release.apk", "sha256": "8eed1c0e9a11367ca496d8f6372dae7805a6bb4f022319de4c139e61f45c8caf", "size": 78159907}, "manifest": {"nativecode": ["x86"], "versionName": "1.29.0", "versionCode": 4293, "usesSdk": {"minSdkVersion": 26, "targetSdkVersion": 35}, "signer": {"sha256": ["f2a0ecf70686447d1d6c6cbbf58c42890500ccf41af372ae2099303980824edd"]}, "usesPermission": [{"name": "android.permission.ACCESS_NETWORK_STATE"}, {"name": "android.permission.BLUETOOTH"}, {"name": "android.permission.BROADCAST_STICKY"}, {"name": "android.permission.CAMERA"}, {"name": "android.permission.DISABLE_KEYGUARD"}, {"name": "android.permission.FOREGROUND_SERVICE"}, {"name": "android.permission.FOREGROUND_SERVICE_PHONE_CALL"}, {"name": "android.permission.FOREGROUND_SERVICE_MICROPHONE"}, {"name": "android.permission.FOREGROUND_SERVICE_SPECIAL_USE"}, {"name": "android.permission.MANAGE_OWN_CALLS"}, {"name": "com.android.launcher.permission.INSTALL_SHORTCUT"}, {"name": "android.permission.INTERNET"}, {"name": "android.app.role.DIALER"}, {"name": "android.permission.MODIFY_AUDIO_SETTINGS"}, {"name": "android.permission.POST_NOTIFICATIONS"}, {"name": "android.permission.RAISED_THREAD_PRIORITY"}, {"name": "android.permission.READ_EXTERNAL_STORAGE"}, {"name": "android.permission.READ_MEDIA_AUDIO"}, {"name": "android.permission.READ_MEDIA_IMAGES"}, {"name": "android.permission.READ_MEDIA_VIDEO"}, {"name": "android.permission.READ_MEDIA_VISUAL_USER_SELECTED"}, {"name": "android.permission.READ_SYNC_SETTINGS"}, {"name": "android.permission.RECEIVE_BOOT_COMPLETED"}, {"name": "android.permission.RECORD_AUDIO"}, {"name": "android.permission.REQUEST_IGNORE_BATTERY_OPTIMIZATIONS"}, {"name": "android.permission.USE_FINGERPRINT"}, {"name": "android.permission.USE_FULL_SCREEN_INTENT"}, {"name": "android.permission.VIBRATE"}, {"name": "android.permission.WAKE_LOCK"}, {"name": "android.permission.WRITE_EXTERNAL_STORAGE"}, {"name": "android.permission.WRITE_SYNC_SETTINGS"}, {"name": "com.google.android.c2dm.permission.RECEIVE"}, {"name": "network.loki.messenger.ACCESS_SESSION_SECRETS"}, {"name": "android.permission.USE_BIOMETRIC"}, {"name": "network.loki.messenger.DYNAMIC_RECEIVER_NOT_EXPORTED_PERMISSION"}]}}, "26fd282a275d8f10cb58301682a8dc4e35426b59ba4c7ef1b7b68f7e01563c1b": {"added": 1762321551000, "file": {"name": "/session-1.29.0-arm64-v8a-fdroid-release.apk", "sha256": "26fd282a275d8f10cb58301682a8dc4e35426b59ba4c7ef1b7b68f7e01563c1b", "size": 76915855}, "manifest": {"nativecode": ["arm64-v8a"], "versionName": "1.29.0", "versionCode": 4292, "usesSdk": {"minSdkVersion": 26, "targetSdkVersion": 35}, "signer": {"sha256": ["f2a0ecf70686447d1d6c6cbbf58c42890500ccf41af372ae2099303980824edd"]}, "usesPermission": [{"name": "android.permission.ACCESS_NETWORK_STATE"}, {"name": "android.permission.BLUETOOTH"}, {"name": "android.permission.BROADCAST_STICKY"}, {"name": "android.permission.CAMERA"}, {"name": "android.permission.DISABLE_KEYGUARD"}, {"name": "android.permission.FOREGROUND_SERVICE"}, {"name": "android.permission.FOREGROUND_SERVICE_PHONE_CALL"}, {"name": "android.permission.FOREGROUND_SERVICE_MICROPHONE"}, {"name": "android.permission.FOREGROUND_SERVICE_SPECIAL_USE"}, {"name": "android.permission.MANAGE_OWN_CALLS"}, {"name": "com.android.launcher.permission.INSTALL_SHORTCUT"}, {"name": "android.permission.INTERNET"}, {"name": "android.app.role.DIALER"}, {"name": "android.permission.MODIFY_AUDIO_SETTINGS"}, {"name": "android.permission.POST_NOTIFICATIONS"}, {"name": "android.permission.RAISED_THREAD_PRIORITY"}, {"name": "android.permission.READ_EXTERNAL_STORAGE"}, {"name": "android.permission.READ_MEDIA_AUDIO"}, {"name": "android.permission.READ_MEDIA_IMAGES"}, {"name": "android.permission.READ_MEDIA_VIDEO"}, {"name": "android.permission.READ_MEDIA_VISUAL_USER_SELECTED"}, {"name": "android.permission.READ_SYNC_SETTINGS"}, {"name": "android.permission.RECEIVE_BOOT_COMPLETED"}, {"name": "android.permission.RECORD_AUDIO"}, {"name": "android.permission.REQUEST_IGNORE_BATTERY_OPTIMIZATIONS"}, {"name": "android.permission.USE_FINGERPRINT"}, {"name": "android.permission.USE_FULL_SCREEN_INTENT"}, {"name": "android.permission.VIBRATE"}, {"name": "android.permission.WAKE_LOCK"}, {"name": "android.permission.WRITE_EXTERNAL_STORAGE"}, {"name": "android.permission.WRITE_SYNC_SETTINGS"}, {"name": "com.google.android.c2dm.permission.RECEIVE"}, {"name": "network.loki.messenger.ACCESS_SESSION_SECRETS"}, {"name": "android.permission.USE_BIOMETRIC"}, {"name": "network.loki.messenger.DYNAMIC_RECEIVER_NOT_EXPORTED_PERMISSION"}]}}, "a86dd9e89f6aaacefb4054fefea1e083512ffd88a9f5552b730eea405aaaf7ea": {"added": 1762321552000, "file": {"name": "/session-1.29.0-armeabi-v7a-fdroid-release.apk", "sha256": "a86dd9e89f6aaacefb4054fefea1e083512ffd88a9f5552b730eea405aaaf7ea", "size": 68361987}, "manifest": {"nativecode": ["armeabi-v7a"], "versionName": "1.29.0", "versionCode": 4291, "usesSdk": {"minSdkVersion": 26, "targetSdkVersion": 35}, "signer": {"sha256": ["f2a0ecf70686447d1d6c6cbbf58c42890500ccf41af372ae2099303980824edd"]}, "usesPermission": [{"name": "android.permission.ACCESS_NETWORK_STATE"}, {"name": "android.permission.BLUETOOTH"}, {"name": "android.permission.BROADCAST_STICKY"}, {"name": "android.permission.CAMERA"}, {"name": "android.permission.DISABLE_KEYGUARD"}, {"name": "android.permission.FOREGROUND_SERVICE"}, {"name": "android.permission.FOREGROUND_SERVICE_PHONE_CALL"}, {"name": "android.permission.FOREGROUND_SERVICE_MICROPHONE"}, {"name": "android.permission.FOREGROUND_SERVICE_SPECIAL_USE"}, {"name": "android.permission.MANAGE_OWN_CALLS"}, {"name": "com.android.launcher.permission.INSTALL_SHORTCUT"}, {"name": "android.permission.INTERNET"}, {"name": "android.app.role.DIALER"}, {"name": "android.permission.MODIFY_AUDIO_SETTINGS"}, {"name": "android.permission.POST_NOTIFICATIONS"}, {"name": "android.permission.RAISED_THREAD_PRIORITY"}, {"name": "android.permission.READ_EXTERNAL_STORAGE"}, {"name": "android.permission.READ_MEDIA_AUDIO"}, {"name": "android.permission.READ_MEDIA_IMAGES"}, {"name": "android.permission.READ_MEDIA_VIDEO"}, {"name": "android.permission.READ_MEDIA_VISUAL_USER_SELECTED"}, {"name": "android.permission.READ_SYNC_SETTINGS"}, {"name": "android.permission.RECEIVE_BOOT_COMPLETED"}, {"name": "android.permission.RECORD_AUDIO"}, {"name": "android.permission.REQUEST_IGNORE_BATTERY_OPTIMIZATIONS"}, {"name": "android.permission.USE_FINGERPRINT"}, {"name": "android.permission.USE_FULL_SCREEN_INTENT"}, {"name": "android.permission.VIBRATE"}, {"name": "android.permission.WAKE_LOCK"}, {"name": "android.permission.WRITE_EXTERNAL_STORAGE"}, {"name": "android.permission.WRITE_SYNC_SETTINGS"}, {"name": "com.google.android.c2dm.permission.RECEIVE"}, {"name": "network.loki.messenger.ACCESS_SESSION_SECRETS"}, {"name": "android.permission.USE_BIOMETRIC"}, {"name": "network.loki.messenger.DYNAMIC_RECEIVER_NOT_EXPORTED_PERMISSION"}]}}, "c6b36f8b74cdf4e034ebfe34009810faab89a0f2a5e5f29c654b368339f936f1": {"added": 1761605799000, "file": {"name": "/session-1.28.2-universal-fdroid-release.apk", "sha256": "c6b36f8b74cdf4e034ebfe34009810faab89a0f2a5e5f29c654b368339f936f1", "size": 143109035}, "manifest": {"nativecode": ["arm64-v8a", "armeabi-v7a", "x86", "x86_64"], "versionName": "1.28.2", "versionCode": 4285, "usesSdk": {"minSdkVersion": 26, "targetSdkVersion": 35}, "signer": {"sha256": ["f2a0ecf70686447d1d6c6cbbf58c42890500ccf41af372ae2099303980824edd"]}, "usesPermission": [{"name": "android.permission.ACCESS_NETWORK_STATE"}, {"name": "android.permission.BLUETOOTH"}, {"name": "android.permission.BROADCAST_STICKY"}, {"name": "android.permission.CAMERA"}, {"name": "android.permission.DISABLE_KEYGUARD"}, {"name": "android.permission.FOREGROUND_SERVICE"}, {"name": "android.permission.FOREGROUND_SERVICE_PHONE_CALL"}, {"name": "android.permission.FOREGROUND_SERVICE_MICROPHONE"}, {"name": "android.permission.FOREGROUND_SERVICE_SPECIAL_USE"}, {"name": "android.permission.MANAGE_OWN_CALLS"}, {"name": "com.android.launcher.permission.INSTALL_SHORTCUT"}, {"name": "android.permission.INTERNET"}, {"name": "android.app.role.DIALER"}, {"name": "android.permission.MODIFY_AUDIO_SETTINGS"}, {"name": "android.permission.POST_NOTIFICATIONS"}, {"name": "android.permission.RAISED_THREAD_PRIORITY"}, {"name": "android.permission.READ_EXTERNAL_STORAGE"}, {"name": "android.permission.READ_MEDIA_AUDIO"}, {"name": "android.permission.READ_MEDIA_IMAGES"}, {"name": "android.permission.READ_MEDIA_VIDEO"}, {"name": "android.permission.READ_MEDIA_VISUAL_USER_SELECTED"}, {"name": "android.permission.READ_SYNC_SETTINGS"}, {"name": "android.permission.RECEIVE_BOOT_COMPLETED"}, {"name": "android.permission.RECORD_AUDIO"}, {"name": "android.permission.REQUEST_IGNORE_BATTERY_OPTIMIZATIONS"}, {"name": "android.permission.USE_FINGERPRINT"}, {"name": "android.permission.USE_FULL_SCREEN_INTENT"}, {"name": "android.permission.VIBRATE"}, {"name": "android.permission.WAKE_LOCK"}, {"name": "android.permission.WRITE_EXTERNAL_STORAGE"}, {"name": "android.permission.WRITE_SYNC_SETTINGS"}, {"name": "com.google.android.c2dm.permission.RECEIVE"}, {"name": "network.loki.messenger.ACCESS_SESSION_SECRETS"}, {"name": "android.permission.USE_BIOMETRIC"}, {"name": "network.loki.messenger.DYNAMIC_RECEIVER_NOT_EXPORTED_PERMISSION"}]}}, "8728366b902764bceb75a513a9ec86123d760ca35e7fe6bd6f7e93f65896f8e2": {"added": 1761605801000, "file": {"name": "/session-1.28.2-x86_64-fdroid-release.apk", "sha256": "8728366b902764bceb75a513a9ec86123d760ca35e7fe6bd6f7e93f65896f8e2", "size": 80962536}, "manifest": {"nativecode": ["x86_64"], "versionName": "1.28.2", "versionCode": 4284, "usesSdk": {"minSdkVersion": 26, "targetSdkVersion": 35}, "signer": {"sha256": ["f2a0ecf70686447d1d6c6cbbf58c42890500ccf41af372ae2099303980824edd"]}, "usesPermission": [{"name": "android.permission.ACCESS_NETWORK_STATE"}, {"name": "android.permission.BLUETOOTH"}, {"name": "android.permission.BROADCAST_STICKY"}, {"name": "android.permission.CAMERA"}, {"name": "android.permission.DISABLE_KEYGUARD"}, {"name": "android.permission.FOREGROUND_SERVICE"}, {"name": "android.permission.FOREGROUND_SERVICE_PHONE_CALL"}, {"name": "android.permission.FOREGROUND_SERVICE_MICROPHONE"}, {"name": "android.permission.FOREGROUND_SERVICE_SPECIAL_USE"}, {"name": "android.permission.MANAGE_OWN_CALLS"}, {"name": "com.android.launcher.permission.INSTALL_SHORTCUT"}, {"name": "android.permission.INTERNET"}, {"name": "android.app.role.DIALER"}, {"name": "android.permission.MODIFY_AUDIO_SETTINGS"}, {"name": "android.permission.POST_NOTIFICATIONS"}, {"name": "android.permission.RAISED_THREAD_PRIORITY"}, {"name": "android.permission.READ_EXTERNAL_STORAGE"}, {"name": "android.permission.READ_MEDIA_AUDIO"}, {"name": "android.permission.READ_MEDIA_IMAGES"}, {"name": "android.permission.READ_MEDIA_VIDEO"}, {"name": "android.permission.READ_MEDIA_VISUAL_USER_SELECTED"}, {"name": "android.permission.READ_SYNC_SETTINGS"}, {"name": "android.permission.RECEIVE_BOOT_COMPLETED"}, {"name": "android.permission.RECORD_AUDIO"}, {"name": "android.permission.REQUEST_IGNORE_BATTERY_OPTIMIZATIONS"}, {"name": "android.permission.USE_FINGERPRINT"}, {"name": "android.permission.USE_FULL_SCREEN_INTENT"}, {"name": "android.permission.VIBRATE"}, {"name": "android.permission.WAKE_LOCK"}, {"name": "android.permission.WRITE_EXTERNAL_STORAGE"}, {"name": "android.permission.WRITE_SYNC_SETTINGS"}, {"name": "com.google.android.c2dm.permission.RECEIVE"}, {"name": "network.loki.messenger.ACCESS_SESSION_SECRETS"}, {"name": "android.permission.USE_BIOMETRIC"}, {"name": "network.loki.messenger.DYNAMIC_RECEIVER_NOT_EXPORTED_PERMISSION"}]}}, "4f422ea3354bdc548c7a39d565b2e7d91aac08b01886d03573f70dcc412551e8": {"added": 1761605800000, "file": {"name": "/session-1.28.2-x86-fdroid-release.apk", "sha256": "4f422ea3354bdc548c7a39d565b2e7d91aac08b01886d03573f70dcc412551e8", "size": 76603268}, "manifest": {"nativecode": ["x86"], "versionName": "1.28.2", "versionCode": 4283, "usesSdk": {"minSdkVersion": 26, "targetSdkVersion": 35}, "signer": {"sha256": ["f2a0ecf70686447d1d6c6cbbf58c42890500ccf41af372ae2099303980824edd"]}, "usesPermission": [{"name": "android.permission.ACCESS_NETWORK_STATE"}, {"name": "android.permission.BLUETOOTH"}, {"name": "android.permission.BROADCAST_STICKY"}, {"name": "android.permission.CAMERA"}, {"name": "android.permission.DISABLE_KEYGUARD"}, {"name": "android.permission.FOREGROUND_SERVICE"}, {"name": "android.permission.FOREGROUND_SERVICE_PHONE_CALL"}, {"name": "android.permission.FOREGROUND_SERVICE_MICROPHONE"}, {"name": "android.permission.FOREGROUND_SERVICE_SPECIAL_USE"}, {"name": "android.permission.MANAGE_OWN_CALLS"}, {"name": "com.android.launcher.permission.INSTALL_SHORTCUT"}, {"name": "android.permission.INTERNET"}, {"name": "android.app.role.DIALER"}, {"name": "android.permission.MODIFY_AUDIO_SETTINGS"}, {"name": "android.permission.POST_NOTIFICATIONS"}, {"name": "android.permission.RAISED_THREAD_PRIORITY"}, {"name": "android.permission.READ_EXTERNAL_STORAGE"}, {"name": "android.permission.READ_MEDIA_AUDIO"}, {"name": "android.permission.READ_MEDIA_IMAGES"}, {"name": "android.permission.READ_MEDIA_VIDEO"}, {"name": "android.permission.READ_MEDIA_VISUAL_USER_SELECTED"}, {"name": "android.permission.READ_SYNC_SETTINGS"}, {"name": "android.permission.RECEIVE_BOOT_COMPLETED"}, {"name": "android.permission.RECORD_AUDIO"}, {"name": "android.permission.REQUEST_IGNORE_BATTERY_OPTIMIZATIONS"}, {"name": "android.permission.USE_FINGERPRINT"}, {"name": "android.permission.USE_FULL_SCREEN_INTENT"}, {"name": "android.permission.VIBRATE"}, {"name": "android.permission.WAKE_LOCK"}, {"name": "android.permission.WRITE_EXTERNAL_STORAGE"}, {"name": "android.permission.WRITE_SYNC_SETTINGS"}, {"name": "com.google.android.c2dm.permission.RECEIVE"}, {"name": "network.loki.messenger.ACCESS_SESSION_SECRETS"}, {"name": "android.permission.USE_BIOMETRIC"}, {"name": "network.loki.messenger.DYNAMIC_RECEIVER_NOT_EXPORTED_PERMISSION"}]}}, "7569ce2a8acdddcc8c18908e7b4af45a35f59add6834bf0c82a6f75d9d68f3c8": {"added": 1761605797000, "file": {"name": "/session-1.28.2-arm64-v8a-fdroid-release.apk", "sha256": "7569ce2a8acdddcc8c18908e7b4af45a35f59add6834bf0c82a6f75d9d68f3c8", "size": 75850736}, "manifest": {"nativecode": ["arm64-v8a"], "versionName": "1.28.2", "versionCode": 4282, "usesSdk": {"minSdkVersion": 26, "targetSdkVersion": 35}, "signer": {"sha256": ["f2a0ecf70686447d1d6c6cbbf58c42890500ccf41af372ae2099303980824edd"]}, "usesPermission": [{"name": "android.permission.ACCESS_NETWORK_STATE"}, {"name": "android.permission.BLUETOOTH"}, {"name": "android.permission.BROADCAST_STICKY"}, {"name": "android.permission.CAMERA"}, {"name": "android.permission.DISABLE_KEYGUARD"}, {"name": "android.permission.FOREGROUND_SERVICE"}, {"name": "android.permission.FOREGROUND_SERVICE_PHONE_CALL"}, {"name": "android.permission.FOREGROUND_SERVICE_MICROPHONE"}, {"name": "android.permission.FOREGROUND_SERVICE_SPECIAL_USE"}, {"name": "android.permission.MANAGE_OWN_CALLS"}, {"name": "com.android.launcher.permission.INSTALL_SHORTCUT"}, {"name": "android.permission.INTERNET"}, {"name": "android.app.role.DIALER"}, {"name": "android.permission.MODIFY_AUDIO_SETTINGS"}, {"name": "android.permission.POST_NOTIFICATIONS"}, {"name": "android.permission.RAISED_THREAD_PRIORITY"}, {"name": "android.permission.READ_EXTERNAL_STORAGE"}, {"name": "android.permission.READ_MEDIA_AUDIO"}, {"name": "android.permission.READ_MEDIA_IMAGES"}, {"name": "android.permission.READ_MEDIA_VIDEO"}, {"name": "android.permission.READ_MEDIA_VISUAL_USER_SELECTED"}, {"name": "android.permission.READ_SYNC_SETTINGS"}, {"name": "android.permission.RECEIVE_BOOT_COMPLETED"}, {"name": "android.permission.RECORD_AUDIO"}, {"name": "android.permission.REQUEST_IGNORE_BATTERY_OPTIMIZATIONS"}, {"name": "android.permission.USE_FINGERPRINT"}, {"name": "android.permission.USE_FULL_SCREEN_INTENT"}, {"name": "android.permission.VIBRATE"}, {"name": "android.permission.WAKE_LOCK"}, {"name": "android.permission.WRITE_EXTERNAL_STORAGE"}, {"name": "android.permission.WRITE_SYNC_SETTINGS"}, {"name": "com.google.android.c2dm.permission.RECEIVE"}, {"name": "network.loki.messenger.ACCESS_SESSION_SECRETS"}, {"name": "android.permission.USE_BIOMETRIC"}, {"name": "network.loki.messenger.DYNAMIC_RECEIVER_NOT_EXPORTED_PERMISSION"}]}}, "683b1f45f723095d0a1e1c15f1c574e4820f3051ba43be3a12b0b66088b41206": {"added": 1761605798000, "file": {"name": "/session-1.28.2-armeabi-v7a-fdroid-release.apk", "sha256": "683b1f45f723095d0a1e1c15f1c574e4820f3051ba43be3a12b0b66088b41206", "size": 67493476}, "manifest": {"nativecode": ["armeabi-v7a"], "versionName": "1.28.2", "versionCode": 4281, "usesSdk": {"minSdkVersion": 26, "targetSdkVersion": 35}, "signer": {"sha256": ["f2a0ecf70686447d1d6c6cbbf58c42890500ccf41af372ae2099303980824edd"]}, "usesPermission": [{"name": "android.permission.ACCESS_NETWORK_STATE"}, {"name": "android.permission.BLUETOOTH"}, {"name": "android.permission.BROADCAST_STICKY"}, {"name": "android.permission.CAMERA"}, {"name": "android.permission.DISABLE_KEYGUARD"}, {"name": "android.permission.FOREGROUND_SERVICE"}, {"name": "android.permission.FOREGROUND_SERVICE_PHONE_CALL"}, {"name": "android.permission.FOREGROUND_SERVICE_MICROPHONE"}, {"name": "android.permission.FOREGROUND_SERVICE_SPECIAL_USE"}, {"name": "android.permission.MANAGE_OWN_CALLS"}, {"name": "com.android.launcher.permission.INSTALL_SHORTCUT"}, {"name": "android.permission.INTERNET"}, {"name": "android.app.role.DIALER"}, {"name": "android.permission.MODIFY_AUDIO_SETTINGS"}, {"name": "android.permission.POST_NOTIFICATIONS"}, {"name": "android.permission.RAISED_THREAD_PRIORITY"}, {"name": "android.permission.READ_EXTERNAL_STORAGE"}, {"name": "android.permission.READ_MEDIA_AUDIO"}, {"name": "android.permission.READ_MEDIA_IMAGES"}, {"name": "android.permission.READ_MEDIA_VIDEO"}, {"name": "android.permission.READ_MEDIA_VISUAL_USER_SELECTED"}, {"name": "android.permission.READ_SYNC_SETTINGS"}, {"name": "android.permission.RECEIVE_BOOT_COMPLETED"}, {"name": "android.permission.RECORD_AUDIO"}, {"name": "android.permission.REQUEST_IGNORE_BATTERY_OPTIMIZATIONS"}, {"name": "android.permission.USE_FINGERPRINT"}, {"name": "android.permission.USE_FULL_SCREEN_INTENT"}, {"name": "android.permission.VIBRATE"}, {"name": "android.permission.WAKE_LOCK"}, {"name": "android.permission.WRITE_EXTERNAL_STORAGE"}, {"name": "android.permission.WRITE_SYNC_SETTINGS"}, {"name": "com.google.android.c2dm.permission.RECEIVE"}, {"name": "network.loki.messenger.ACCESS_SESSION_SECRETS"}, {"name": "android.permission.USE_BIOMETRIC"}, {"name": "network.loki.messenger.DYNAMIC_RECEIVER_NOT_EXPORTED_PERMISSION"}]}}, "d57962e04c1775d7a0c0eb7e306471d16810de478d5745b9a20721e5c9818220": {"added": 1759896361000, "file": {"name": "/session-1.28.1-universal-fdroid-release.apk", "sha256": "d57962e04c1775d7a0c0eb7e306471d16810de478d5745b9a20721e5c9818220", "size": 143109035}, "manifest": {"nativecode": ["arm64-v8a", "armeabi-v7a", "x86", "x86_64"], "versionName": "1.28.1", "versionCode": 4265, "usesSdk": {"minSdkVersion": 26, "targetSdkVersion": 35}, "signer": {"sha256": ["f2a0ecf70686447d1d6c6cbbf58c42890500ccf41af372ae2099303980824edd"]}, "usesPermission": [{"name": "android.permission.ACCESS_NETWORK_STATE"}, {"name": "android.permission.BLUETOOTH"}, {"name": "android.permission.BROADCAST_STICKY"}, {"name": "android.permission.CAMERA"}, {"name": "android.permission.DISABLE_KEYGUARD"}, {"name": "android.permission.FOREGROUND_SERVICE"}, {"name": "android.permission.FOREGROUND_SERVICE_PHONE_CALL"}, {"name": "android.permission.FOREGROUND_SERVICE_MICROPHONE"}, {"name": "android.permission.FOREGROUND_SERVICE_SPECIAL_USE"}, {"name": "android.permission.MANAGE_OWN_CALLS"}, {"name": "com.android.launcher.permission.INSTALL_SHORTCUT"}, {"name": "android.permission.INTERNET"}, {"name": "android.app.role.DIALER"}, {"name": "android.permission.MODIFY_AUDIO_SETTINGS"}, {"name": "android.permission.POST_NOTIFICATIONS"}, {"name": "android.permission.RAISED_THREAD_PRIORITY"}, {"name": "android.permission.READ_EXTERNAL_STORAGE"}, {"name": "android.permission.READ_MEDIA_AUDIO"}, {"name": "android.permission.READ_MEDIA_IMAGES"}, {"name": "android.permission.READ_MEDIA_VIDEO"}, {"name": "android.permission.READ_MEDIA_VISUAL_USER_SELECTED"}, {"name": "android.permission.READ_SYNC_SETTINGS"}, {"name": "android.permission.RECEIVE_BOOT_COMPLETED"}, {"name": "android.permission.RECORD_AUDIO"}, {"name": "android.permission.REQUEST_IGNORE_BATTERY_OPTIMIZATIONS"}, {"name": "android.permission.USE_FINGERPRINT"}, {"name": "android.permission.USE_FULL_SCREEN_INTENT"}, {"name": "android.permission.VIBRATE"}, {"name": "android.permission.WAKE_LOCK"}, {"name": "android.permission.WRITE_EXTERNAL_STORAGE"}, {"name": "android.permission.WRITE_SYNC_SETTINGS"}, {"name": "com.google.android.c2dm.permission.RECEIVE"}, {"name": "network.loki.messenger.ACCESS_SESSION_SECRETS"}, {"name": "android.permission.USE_BIOMETRIC"}, {"name": "network.loki.messenger.DYNAMIC_RECEIVER_NOT_EXPORTED_PERMISSION"}]}}, "5667a73d9a86a2ba6e6ddef7f9023f08f88bedd85a8c9d87a0c9baae871bd296": {"added": 1759896363000, "file": {"name": "/session-1.28.1-x86_64-fdroid-release.apk", "sha256": "5667a73d9a86a2ba6e6ddef7f9023f08f88bedd85a8c9d87a0c9baae871bd296", "size": 80962540}, "manifest": {"nativecode": ["x86_64"], "versionName": "1.28.1", "versionCode": 4264, "usesSdk": {"minSdkVersion": 26, "targetSdkVersion": 35}, "signer": {"sha256": ["f2a0ecf70686447d1d6c6cbbf58c42890500ccf41af372ae2099303980824edd"]}, "usesPermission": [{"name": "android.permission.ACCESS_NETWORK_STATE"}, {"name": "android.permission.BLUETOOTH"}, {"name": "android.permission.BROADCAST_STICKY"}, {"name": "android.permission.CAMERA"}, {"name": "android.permission.DISABLE_KEYGUARD"}, {"name": "android.permission.FOREGROUND_SERVICE"}, {"name": "android.permission.FOREGROUND_SERVICE_PHONE_CALL"}, {"name": "android.permission.FOREGROUND_SERVICE_MICROPHONE"}, {"name": "android.permission.FOREGROUND_SERVICE_SPECIAL_USE"}, {"name": "android.permission.MANAGE_OWN_CALLS"}, {"name": "com.android.launcher.permission.INSTALL_SHORTCUT"}, {"name": "android.permission.INTERNET"}, {"name": "android.app.role.DIALER"}, {"name": "android.permission.MODIFY_AUDIO_SETTINGS"}, {"name": "android.permission.POST_NOTIFICATIONS"}, {"name": "android.permission.RAISED_THREAD_PRIORITY"}, {"name": "android.permission.READ_EXTERNAL_STORAGE"}, {"name": "android.permission.READ_MEDIA_AUDIO"}, {"name": "android.permission.READ_MEDIA_IMAGES"}, {"name": "android.permission.READ_MEDIA_VIDEO"}, {"name": "android.permission.READ_MEDIA_VISUAL_USER_SELECTED"}, {"name": "android.permission.READ_SYNC_SETTINGS"}, {"name": "android.permission.RECEIVE_BOOT_COMPLETED"}, {"name": "android.permission.RECORD_AUDIO"}, {"name": "android.permission.REQUEST_IGNORE_BATTERY_OPTIMIZATIONS"}, {"name": "android.permission.USE_FINGERPRINT"}, {"name": "android.permission.USE_FULL_SCREEN_INTENT"}, {"name": "android.permission.VIBRATE"}, {"name": "android.permission.WAKE_LOCK"}, {"name": "android.permission.WRITE_EXTERNAL_STORAGE"}, {"name": "android.permission.WRITE_SYNC_SETTINGS"}, {"name": "com.google.android.c2dm.permission.RECEIVE"}, {"name": "network.loki.messenger.ACCESS_SESSION_SECRETS"}, {"name": "android.permission.USE_BIOMETRIC"}, {"name": "network.loki.messenger.DYNAMIC_RECEIVER_NOT_EXPORTED_PERMISSION"}]}}, "52661feba0cbb52832aa7a55f4abd1f40107376c4b02a3b233b98c87ec874cd1": {"added": 1759896362000, "file": {"name": "/session-1.28.1-x86-fdroid-release.apk", "sha256": "52661feba0cbb52832aa7a55f4abd1f40107376c4b02a3b233b98c87ec874cd1", "size": 76603272}, "manifest": {"nativecode": ["x86"], "versionName": "1.28.1", "versionCode": 4263, "usesSdk": {"minSdkVersion": 26, "targetSdkVersion": 35}, "signer": {"sha256": ["f2a0ecf70686447d1d6c6cbbf58c42890500ccf41af372ae2099303980824edd"]}, "usesPermission": [{"name": "android.permission.ACCESS_NETWORK_STATE"}, {"name": "android.permission.BLUETOOTH"}, {"name": "android.permission.BROADCAST_STICKY"}, {"name": "android.permission.CAMERA"}, {"name": "android.permission.DISABLE_KEYGUARD"}, {"name": "android.permission.FOREGROUND_SERVICE"}, {"name": "android.permission.FOREGROUND_SERVICE_PHONE_CALL"}, {"name": "android.permission.FOREGROUND_SERVICE_MICROPHONE"}, {"name": "android.permission.FOREGROUND_SERVICE_SPECIAL_USE"}, {"name": "android.permission.MANAGE_OWN_CALLS"}, {"name": "com.android.launcher.permission.INSTALL_SHORTCUT"}, {"name": "android.permission.INTERNET"}, {"name": "android.app.role.DIALER"}, {"name": "android.permission.MODIFY_AUDIO_SETTINGS"}, {"name": "android.permission.POST_NOTIFICATIONS"}, {"name": "android.permission.RAISED_THREAD_PRIORITY"}, {"name": "android.permission.READ_EXTERNAL_STORAGE"}, {"name": "android.permission.READ_MEDIA_AUDIO"}, {"name": "android.permission.READ_MEDIA_IMAGES"}, {"name": "android.permission.READ_MEDIA_VIDEO"}, {"name": "android.permission.READ_MEDIA_VISUAL_USER_SELECTED"}, {"name": "android.permission.READ_SYNC_SETTINGS"}, {"name": "android.permission.RECEIVE_BOOT_COMPLETED"}, {"name": "android.permission.RECORD_AUDIO"}, {"name": "android.permission.REQUEST_IGNORE_BATTERY_OPTIMIZATIONS"}, {"name": "android.permission.USE_FINGERPRINT"}, {"name": "android.permission.USE_FULL_SCREEN_INTENT"}, {"name": "android.permission.VIBRATE"}, {"name": "android.permission.WAKE_LOCK"}, {"name": "android.permission.WRITE_EXTERNAL_STORAGE"}, {"name": "android.permission.WRITE_SYNC_SETTINGS"}, {"name": "com.google.android.c2dm.permission.RECEIVE"}, {"name": "network.loki.messenger.ACCESS_SESSION_SECRETS"}, {"name": "android.permission.USE_BIOMETRIC"}, {"name": "network.loki.messenger.DYNAMIC_RECEIVER_NOT_EXPORTED_PERMISSION"}]}}, "844b07346ed8b2a895a8f1e73c67af52823acc8f8a5ada893371c2c05b38e78b": {"added": 1759896359000, "file": {"name": "/session-1.28.1-arm64-v8a-fdroid-release.apk", "sha256": "844b07346ed8b2a895a8f1e73c67af52823acc8f8a5ada893371c2c05b38e78b", "size": 75850740}, "manifest": {"nativecode": ["arm64-v8a"], "versionName": "1.28.1", "versionCode": 4262, "usesSdk": {"minSdkVersion": 26, "targetSdkVersion": 35}, "signer": {"sha256": ["f2a0ecf70686447d1d6c6cbbf58c42890500ccf41af372ae2099303980824edd"]}, "usesPermission": [{"name": "android.permission.ACCESS_NETWORK_STATE"}, {"name": "android.permission.BLUETOOTH"}, {"name": "android.permission.BROADCAST_STICKY"}, {"name": "android.permission.CAMERA"}, {"name": "android.permission.DISABLE_KEYGUARD"}, {"name": "android.permission.FOREGROUND_SERVICE"}, {"name": "android.permission.FOREGROUND_SERVICE_PHONE_CALL"}, {"name": "android.permission.FOREGROUND_SERVICE_MICROPHONE"}, {"name": "android.permission.FOREGROUND_SERVICE_SPECIAL_USE"}, {"name": "android.permission.MANAGE_OWN_CALLS"}, {"name": "com.android.launcher.permission.INSTALL_SHORTCUT"}, {"name": "android.permission.INTERNET"}, {"name": "android.app.role.DIALER"}, {"name": "android.permission.MODIFY_AUDIO_SETTINGS"}, {"name": "android.permission.POST_NOTIFICATIONS"}, {"name": "android.permission.RAISED_THREAD_PRIORITY"}, {"name": "android.permission.READ_EXTERNAL_STORAGE"}, {"name": "android.permission.READ_MEDIA_AUDIO"}, {"name": "android.permission.READ_MEDIA_IMAGES"}, {"name": "android.permission.READ_MEDIA_VIDEO"}, {"name": "android.permission.READ_MEDIA_VISUAL_USER_SELECTED"}, {"name": "android.permission.READ_SYNC_SETTINGS"}, {"name": "android.permission.RECEIVE_BOOT_COMPLETED"}, {"name": "android.permission.RECORD_AUDIO"}, {"name": "android.permission.REQUEST_IGNORE_BATTERY_OPTIMIZATIONS"}, {"name": "android.permission.USE_FINGERPRINT"}, {"name": "android.permission.USE_FULL_SCREEN_INTENT"}, {"name": "android.permission.VIBRATE"}, {"name": "android.permission.WAKE_LOCK"}, {"name": "android.permission.WRITE_EXTERNAL_STORAGE"}, {"name": "android.permission.WRITE_SYNC_SETTINGS"}, {"name": "com.google.android.c2dm.permission.RECEIVE"}, {"name": "network.loki.messenger.ACCESS_SESSION_SECRETS"}, {"name": "android.permission.USE_BIOMETRIC"}, {"name": "network.loki.messenger.DYNAMIC_RECEIVER_NOT_EXPORTED_PERMISSION"}]}}, "52e5c3723efd00084dec7ec44caed2a4f574417bde6956845a6ea20c232e5f1f": {"added": 1759896360000, "file": {"name": "/session-1.28.1-armeabi-v7a-fdroid-release.apk", "sha256": "52e5c3723efd00084dec7ec44caed2a4f574417bde6956845a6ea20c232e5f1f", "size": 67493480}, "manifest": {"nativecode": ["armeabi-v7a"], "versionName": "1.28.1", "versionCode": 4261, "usesSdk": {"minSdkVersion": 26, "targetSdkVersion": 35}, "signer": {"sha256": ["f2a0ecf70686447d1d6c6cbbf58c42890500ccf41af372ae2099303980824edd"]}, "usesPermission": [{"name": "android.permission.ACCESS_NETWORK_STATE"}, {"name": "android.permission.BLUETOOTH"}, {"name": "android.permission.BROADCAST_STICKY"}, {"name": "android.permission.CAMERA"}, {"name": "android.permission.DISABLE_KEYGUARD"}, {"name": "android.permission.FOREGROUND_SERVICE"}, {"name": "android.permission.FOREGROUND_SERVICE_PHONE_CALL"}, {"name": "android.permission.FOREGROUND_SERVICE_MICROPHONE"}, {"name": "android.permission.FOREGROUND_SERVICE_SPECIAL_USE"}, {"name": "android.permission.MANAGE_OWN_CALLS"}, {"name": "com.android.launcher.permission.INSTALL_SHORTCUT"}, {"name": "android.permission.INTERNET"}, {"name": "android.app.role.DIALER"}, {"name": "android.permission.MODIFY_AUDIO_SETTINGS"}, {"name": "android.permission.POST_NOTIFICATIONS"}, {"name": "android.permission.RAISED_THREAD_PRIORITY"}, {"name": "android.permission.READ_EXTERNAL_STORAGE"}, {"name": "android.permission.READ_MEDIA_AUDIO"}, {"name": "android.permission.READ_MEDIA_IMAGES"}, {"name": "android.permission.READ_MEDIA_VIDEO"}, {"name": "android.permission.READ_MEDIA_VISUAL_USER_SELECTED"}, {"name": "android.permission.READ_SYNC_SETTINGS"}, {"name": "android.permission.RECEIVE_BOOT_COMPLETED"}, {"name": "android.permission.RECORD_AUDIO"}, {"name": "android.permission.REQUEST_IGNORE_BATTERY_OPTIMIZATIONS"}, {"name": "android.permission.USE_FINGERPRINT"}, {"name": "android.permission.USE_FULL_SCREEN_INTENT"}, {"name": "android.permission.VIBRATE"}, {"name": "android.permission.WAKE_LOCK"}, {"name": "android.permission.WRITE_EXTERNAL_STORAGE"}, {"name": "android.permission.WRITE_SYNC_SETTINGS"}, {"name": "com.google.android.c2dm.permission.RECEIVE"}, {"name": "network.loki.messenger.ACCESS_SESSION_SECRETS"}, {"name": "android.permission.USE_BIOMETRIC"}, {"name": "network.loki.messenger.DYNAMIC_RECEIVER_NOT_EXPORTED_PERMISSION"}]}}}}}}